MANIFEST.in
README.rst
setup.py
collective/__init__.py
collective.pfg.userjoin.egg-info/PKG-INFO
collective.pfg.userjoin.egg-info/SOURCES.txt
collective.pfg.userjoin.egg-info/dependency_links.txt
collective.pfg.userjoin.egg-info/entry_points.txt
collective.pfg.userjoin.egg-info/namespace_packages.txt
collective.pfg.userjoin.egg-info/not-zip-safe
collective.pfg.userjoin.egg-info/requires.txt
collective.pfg.userjoin.egg-info/top_level.txt
collective/pfg/__init__.py
collective/pfg/userjoin/__init__.py
collective/pfg/userjoin/config.py
collective/pfg/userjoin/configure.zcml
collective/pfg/userjoin/content.py
collective/pfg/userjoin/interfaces.py
collective/pfg/userjoin/setuphandlers.py
collective/pfg/userjoin/browser/__init__.py
collective/pfg/userjoin/browser/configure.zcml
collective/pfg/userjoin/browser/join-detail.pt
collective/pfg/userjoin/browser/userjoin-adapter.pt
collective/pfg/userjoin/browser/view.py
collective/pfg/userjoin/locales/collective.pfg.userjoin-manual.pot
collective/pfg/userjoin/locales/collective.pfg.userjoin.pot
collective/pfg/userjoin/locales/runI18ndude.sh
collective/pfg/userjoin/locales/it/LC_MESSAGES/collective.pfg.userjoin.mo
collective/pfg/userjoin/locales/it/LC_MESSAGES/collective.pfg.userjoin.po
collective/pfg/userjoin/profiles/default/collective.pfg.userjoin_various.txt
collective/pfg/userjoin/profiles/default/factorytool.xml
collective/pfg/userjoin/profiles/default/metadata.xml
collective/pfg/userjoin/profiles/default/rolemap.xml
collective/pfg/userjoin/profiles/default/types.xml
collective/pfg/userjoin/profiles/default/workflows.xml
collective/pfg/userjoin/profiles/default/types/UserJoinAdapter.xml
docs/HISTORY.rst
docs/INSTALL.txt
docs/LICENSE.GPL
docs/LICENSE.txt
docs/collective.pfg.userjoin.0.1.0-01.png
docs/collective.pfg.userjoin.0.1.0-02.png
docs/collective.pfg.userjoin.0.1.0-03.png
docs/collective.pfg.userjoin.0.1.0-04.png