Metadata-Version: 1.0
Name: collective.pfg.userjoin
Version: 0.1.0
Summary: A PloneFormGen adapter for subscribe users to the site
Home-page: http://github.com/PloneGov-IT/collective.pfg.userjoin
Author: RedTurtle Technology
Author-email: sviluppoplone@redturtle.it
License: GPL
Keywords: plone plonegov ploneformgen user subscription
Platform: UNKNOWN
Classifier: Framework :: Plone
Classifier: Framework :: Plone :: 4.3
Classifier: Programming Language :: Python
